blockchain/__init__.py
blockchain/block.py
blockchain/constants.py
blockchain/reader.py
blockchain/script.py
pyblockchain-0.2.2.dist-info/DESCRIPTION.rst
pyblockchain-0.2.2.dist-info/METADATA
pyblockchain-0.2.2.dist-info/RECORD
pyblockchain-0.2.2.dist-info/WHEEL
pyblockchain-0.2.2.dist-info/metadata.json
pyblockchain-0.2.2.dist-info/top_level.txt
