Metadata-Version: 2.0
Name: pyblockchain
Version: 0.2.2
Summary: pyblockchain is a Python library for parsing blockchain data
Home-page: https://github.com/toidi/pyblockchain
Author: Eduard Iskandarov
Author-email: eduard.iskandarov@yandex.ru
License: BSD
Keywords: blockchain bitcoin altcoin
Platform: UNKNOWN
Classifier: Development Status :: 3 - Alpha
Classifier: Intended Audience :: Developers
Classifier: License :: OSI Approved :: BSD License
Classifier: Programming Language :: Python :: 3.5
Classifier: Programming Language :: Python :: 3 :: Only
Classifier: Topic :: Software Development :: Libraries :: Python Modules
Requires-Dist: base58
